hera_qm/__init__.py
hera_qm/_version.py
hera_qm/ant_class.py
hera_qm/ant_metrics.py
hera_qm/auto_metrics.py
hera_qm/firstcal_metrics.py
hera_qm/metrics_io.py
hera_qm/omnical_metrics.py
hera_qm/time_series_metrics.py
hera_qm/utils.py
hera_qm/vis_metrics.py
hera_qm/xrfi.py
hera_qm/data/__init__.py
hera_qm/data/a_priori_flags_integrations.yaml
hera_qm/data/a_priori_flags_jds.yaml
hera_qm/data/a_priori_flags_lsts.yaml
hera_qm/data/a_priori_flags_maximum_channels.yaml
hera_qm/data/a_priori_flags_maximum_integrations.yaml
hera_qm/data/a_priori_flags_negative_channels.yaml
hera_qm/data/a_priori_flags_negative_integrations.yaml
hera_qm/data/a_priori_flags_no_ants.yaml
hera_qm/data/a_priori_flags_no_chans.yaml
hera_qm/data/a_priori_flags_no_flags.yaml
hera_qm/data/a_priori_flags_no_integrations.yaml
hera_qm/data/a_priori_flags_old_pols.yaml
hera_qm/data/a_priori_flags_sample.yaml
hera_qm/data/antenna_flags.h5
hera_qm/data/example_ant_metrics.hdf5
hera_qm/data/example_ant_metrics.json
hera_qm/data/example_ant_metrics_all_string.json
hera_qm/data/example_firstcal_metrics.hdf5
hera_qm/data/example_firstcal_metrics.json
hera_qm/data/example_omnical_metrics.hdf5
hera_qm/data/example_omnical_metrics.json
hera_qm/data/example_two_polarization_firstcal_results.hdf5
hera_qm/data/heratest_calfile.py
hera_qm/data/test_detrend_meanfilt_ans.txt
hera_qm/data/test_detrend_medfilt_ans_v2.txt
hera_qm/data/test_detrend_medfilt_complex_ans_v2.txt
hera_qm/data/test_detrend_medminfilt_ans.txt
hera_qm/data/zen.2457555.42443.HH.uvcA.omni.calfits
hera_qm/data/zen.2457555.42443.xx.HH.uvcA.bad.first.calfits
hera_qm/data/zen.2457555.42443.xx.HH.uvcA.bad.omni.calfits
hera_qm/data/zen.2457555.42443.xx.HH.uvcA.first.calfits
hera_qm/data/zen.2457555.42443.xx.HH.uvcA.good.omni.calfits
hera_qm/data/zen.2457555.42443.xx.HH.uvcA.reallybad.first.calfits
hera_qm/data/zen.2457555.42443.xx.HH.uvcA.reallybad.omni.calfits
hera_qm/data/zen.2457555.42443.yy.HH.uvcA.first.calfits
hera_qm-2.2.0.dist-info/LICENSE
hera_qm-2.2.0.dist-info/METADATA
hera_qm-2.2.0.dist-info/WHEEL
hera_qm-2.2.0.dist-info/entry_points.txt
hera_qm-2.2.0.dist-info/top_level.txt
hera_qm-2.2.0.dist-info/RECORD
