Metadata-Version: 2.1
Name: hera_qm
Version: 2.2.0
Summary: HERA Data Quality Metrics.
Author: HERA Team
License: MIT
Project-URL: repository, https://github.com/HERA-Team/hera_qm
Classifier: Programming Language :: Python :: 3
Requires-Python: >=3.9
License-File: LICENSE
Requires-Dist: numpy >1.23
Requires-Dist: astropy >=5.0.4
Requires-Dist: h5py >=3.1
Requires-Dist: pyyaml
Requires-Dist: pyuvdata >=3.0
Requires-Dist: hera-filters
Provides-Extra: all
Requires-Dist: hera-qm[tests] ; extra == 'all'
Provides-Extra: tests
Requires-Dist: pytest ; extra == 'tests'
Requires-Dist: pytest-cov ; extra == 'tests'
Requires-Dist: hera-calibration ; extra == 'tests'
